docs/configuration.md
docs/experiments.md
docs/gen_ref_nav.py
docs/index.md
docs/install.md
safe_autonomy_sims/__init__.py
safe_autonomy_sims/agents/__init__.py
safe_autonomy_sims/agents/rta_agent.py
safe_autonomy_sims/dones/__init__.py
safe_autonomy_sims/dones/common_dones.py
safe_autonomy_sims/dones/cwh/__init__.py
safe_autonomy_sims/dones/cwh/common.py
safe_autonomy_sims/dones/cwh/docking_dones.py
safe_autonomy_sims/dones/cwh/inspection_dones.py
safe_autonomy_sims/evaluation/__init__.py
safe_autonomy_sims/evaluation/animation/__init__.py
safe_autonomy_sims/evaluation/animation/base_animation.py
safe_autonomy_sims/evaluation/animation/inspection_animation.py
safe_autonomy_sims/evaluation/animation/six_dof_animation.py
safe_autonomy_sims/evaluation/evaluation_api.py
safe_autonomy_sims/evaluation/general_metrics.py
safe_autonomy_sims/evaluation/inspection_metrics.py
safe_autonomy_sims/evaluation/launch/__init__.py
safe_autonomy_sims/evaluation/launch/serialize_cwh3d.py
safe_autonomy_sims/experiments/__init__.py
safe_autonomy_sims/experiments/rllib_api_experiment.py
safe_autonomy_sims/experiments/safe_autonomy_rllib_api_experiment.py
safe_autonomy_sims/glues/__init__.py
safe_autonomy_sims/glues/coordinate_axis_glue.py
safe_autonomy_sims/glues/dot_product_glue.py
safe_autonomy_sims/glues/magnitude_glue.py
safe_autonomy_sims/glues/rta_glue.py
safe_autonomy_sims/glues/six_dof_glues.py
safe_autonomy_sims/glues/vel_limit_glue.py
safe_autonomy_sims/gym/__init__.py
safe_autonomy_sims/gym/docking/__init__.py
safe_autonomy_sims/gym/docking/docking_v0.py
safe_autonomy_sims/gym/docking/reward.py
safe_autonomy_sims/gym/docking/utils.py
safe_autonomy_sims/gym/inspection/__init__.py
safe_autonomy_sims/gym/inspection/inspection_v0.py
safe_autonomy_sims/gym/inspection/reward.py
safe_autonomy_sims/gym/inspection/sixdof_inspection_v0.py
safe_autonomy_sims/gym/inspection/utils.py
safe_autonomy_sims/gym/inspection/weighted_inspection_v0.py
safe_autonomy_sims/pettingzoo/__init__.py
safe_autonomy_sims-4.2.3.dist-info/LICENSE
safe_autonomy_sims-4.2.3.dist-info/METADATA
safe_autonomy_sims-4.2.3.dist-info/WHEEL
safe_autonomy_sims-4.2.3.dist-info/RECORD
