Metadata-Version: 2.1
Name: safe-autonomy-sims
Version: 4.2.3
Summary: The Safe-Autonomy-Sims library provides the components and tools to build modular, integration-focused Reinforcement Learning environments with Run Time Assurance (RTA)
Home-page: https://github.com/act3-ace/safe-autonomy-sims.git
Author: Charles Keating
Author-email: Charles.Keating@udri.udayton.edu
Requires-Python: >=3.10,<3.11
Classifier: Operating System :: OS Independent
Classifier: Programming Language :: Python :: 3
Classifier: Programming Language :: Python :: 3.10
Requires-Dist: corl (>=3.16.2,<4.0.0)
Requires-Dist: imageio (==2.25.0)
Requires-Dist: imageio-ffmpeg (==0.4.8)
Requires-Dist: numpy (>=1.25.0,<2.0.0)
Requires-Dist: pettingzoo (>=1.24.3,<2.0.0)
Requires-Dist: run-time-assurance (>=1.18.5,<2.0.0)
Requires-Dist: safe-autonomy-simulation (>=2.1.2,<3.0.0)
Requires-Dist: scikit-learn (>=1.3.0,<2.0.0)
Requires-Dist: seaborn (>=0.12.0,<0.13.0)
Requires-Dist: setuptools (>=69.5.1,<70.0.0)
Requires-Dist: torch (>=2.0.0,!=2.0.1,!=2.1.0)
Requires-Dist: tqdm (>=4.66.1,<5.0.0)
Project-URL: Documentation, https://github.com/act3-ace/safe-autonomy-sims/docs
Project-URL: Repository, https://github.com/act3-ace/safe-autonomy-sims.git
